bhp_pro.py
bhp_pro-1.2.9.dist-info/METADATA
bhp_pro-1.2.9.dist-info/WHEEL
bhp_pro-1.2.9.dist-info/entry_points.txt
bhp_pro-1.2.9.dist-info/top_level.txt
bhp_pro-1.2.9.dist-info/RECORD
